pydevice2mqtt/__init__.py
pydevice2mqtt/pydevice2mqtt.py
pydevice2mqtt/remote_devices.py
pydevice2mqtt-0.2.5.dist-info/entry_points.txt
pydevice2mqtt-0.2.5.dist-info/LICENSE
pydevice2mqtt-0.2.5.dist-info/WHEEL
pydevice2mqtt-0.2.5.dist-info/METADATA
pydevice2mqtt-0.2.5.dist-info/RECORD
