Metadata-Version: 2.1
Name: pydevice2mqtt
Version: 0.2.5
Summary:     This project provides a simplified control of devices via MQTT.
Keywords: hassio,mqtt,homeassistent,homeautomation
Author-email: HighImp <AnyHighZ@gmail.com>
Requires-Python: >=3.7
Requires-Dist: paho-mqtt
Requires-Dist: pyyaml
Requires-Dist: pylint ~=2.14.0 ; extra == "test"
Requires-Dist: pytest-cov ~=4.0.0 ; extra == "test"
Requires-Dist: pytest-mock ~=3.10.0 ; extra == "test"
Provides-Extra: test
